pyaswasm/__init__.py
pyaswasm-1.0.2.dist-info/LICENSE
pyaswasm-1.0.2.dist-info/METADATA
pyaswasm-1.0.2.dist-info/WHEEL
pyaswasm-1.0.2.dist-info/top_level.txt
pyaswasm-1.0.2.dist-info/RECORD
