Metadata-Version: 2.1
Name: pyaswasm
Version: 1.0.2
Summary: Loader of AssemblyScript WASM modules into Python with Wasmer backend
Home-page: https://github.com/Tugcga/pyaswasm
Author: Shekn Itrch
Author-email: cgproggame@gmail.com
License: UNKNOWN
Project-URL: Bug Tracker, https://github.com/Tugcga/pyaswasm/issues
Platform: UNKNOWN
Classifier: Programming Language :: Python :: 3
Classifier: License :: OSI Approved :: MIT License
Classifier: Operating System :: OS Independent
Requires-Python: >=3.6
License-File: LICENSE
Requires-Dist: wasmer
